enforce_host/__init__.py
enforce_host/tests/__init__.py
enforce_host/tests/settings.py
enforce_host/tests/tests.py
enforce_host/tests/urls.py
django_enforce_host-1.1.0.dist-info/LICENSE
django_enforce_host-1.1.0.dist-info/METADATA
django_enforce_host-1.1.0.dist-info/WHEEL
django_enforce_host-1.1.0.dist-info/top_level.txt
django_enforce_host-1.1.0.dist-info/RECORD
