Metadata-Version: 2.1
Name: django-enforce-host
Version: 1.1.0
Summary: Middleware to redirect requests to a canonical hostname
Home-page: https://github.com/dabapps/django-enforce-host
Author: DabApps
Author-email: hello@dabapps.com
License: BSD
Platform: UNKNOWN
